{
	"Order": 114,
	"Type": "meccan",
	"Arabic": {
		"Name": "الناس",
		"Lines": [
			"قُلۡ أَعُوذُ بِرَبِّ ٱلنَّاسِ",
			"مَلِكِ ٱلنَّاسِ",
			"إِلَٰهِ ٱلنَّاسِ",
			"مِن شَرِّ ٱلۡوَسۡوَاسِ ٱلۡخَنَّاسِ",
			"ٱلَّذِي يُوَسۡوِسُ فِي صُدُورِ ٱلنَّاسِ",
			"مِنَ ٱلۡجِنَّةِ وَٱلنَّاسِ"
		]
	},
	"English": {
		"Name": "An-Nas",
		"Description": "Mankind",
		"Lines": [
			"Say, \"I seek refuge in the Lord of mankind",
			"The Sovereign of mankind",
			"The God of mankind",
			"From the evil of the retreating whisperer",
			"Who whispers [evil] into the breasts of mankind",
			"From among the jinn and mankind"
		]
	},
	"Turkish": {
		"Name": "NAS",
		"Description": "İnsanlar",
		"Lines": [
			"İyiliği sonsuz, ikramı bol Allah’ın adıyla,",
			"De ki: “Sığınırım insanlığın Sahibine,",
			"insanlığın hükümdarına,",
			"insanlığın İlahına!",
			"Sinsice kötülükler fısıldayanların şerrinden sığınırım.",
			"Kötülüğü insanların içilerine fısıldayandan!"
		]
	}
}